sk_lib/__init__.py
sk_lib/network/__init__.py
sk_lib/network/ssh_tool.py
shikou_lib-0.0.2.dist-info/METADATA
shikou_lib-0.0.2.dist-info/WHEEL
shikou_lib-0.0.2.dist-info/top_level.txt
shikou_lib-0.0.2.dist-info/RECORD
