Metadata-Version: 2.4
Name: shikou-lib
Version: 0.0.2
Summary: 常用操作工具库
License: MIT
Project-URL: Repository, https://github.com/shikou-git/shikou-lib
Requires-Python: >=3.10
Requires-Dist: paramiko
Requires-Dist: loguru
